sphinxcontrib_dd-0.1.7-py3.6-nspkg.pth
sphinxcontrib/dd/__init__.py
sphinxcontrib/dd/data_dictionary.py
sphinxcontrib/dd/database_diagram.py
sphinxcontrib/dd/yaml.py
sphinxcontrib_dd-0.1.7.dist-info/DESCRIPTION.rst
sphinxcontrib_dd-0.1.7.dist-info/METADATA
sphinxcontrib_dd-0.1.7.dist-info/RECORD
sphinxcontrib_dd-0.1.7.dist-info/WHEEL
sphinxcontrib_dd-0.1.7.dist-info/metadata.json
sphinxcontrib_dd-0.1.7.dist-info/namespace_packages.txt
sphinxcontrib_dd-0.1.7.dist-info/top_level.txt
