Metadata-Version: 2.0
Name: sphinxcontrib-dd
Version: 0.1.7
Summary: Sphinx extension for Data Dictionary and Database Diagram
Home-page: https://github.com/julot/sphinxcontrib-dd
Author: Andy Yulius
Author-email: julot@gmail.com
License: MIT
Keywords: sphinx sphinxcontrib data dictionary database diagram
Platform: any
Classifier: Development Status :: 3 - Alpha
Classifier: Environment :: Console
Classifier: Intended Audience :: Developers
Classifier: License :: OSI Approved :: MIT License
Classifier: Operating System :: OS Independent
Classifier: Programming Language :: Python
Classifier: Topic :: Documentation
Classifier: Topic :: Utilities
Requires-Dist: PyYAML (>=3.12)
Requires-Dist: Sphinx (>=0.6)
Requires-Dist: jsonschema (>=2.5.1)
Requires-Dist: recommonmark (>=0.4.0)
